hubstaff_mcp/__init__.py
hubstaff_mcp/server.py
hubstaff_mcp-0.1.3.dist-info/METADATA
hubstaff_mcp-0.1.3.dist-info/WHEEL
hubstaff_mcp-0.1.3.dist-info/entry_points.txt
hubstaff_mcp-0.1.3.dist-info/licenses/LICENSE
hubstaff_mcp-0.1.3.dist-info/RECORD
