Metadata-Version: 2.4
Name: hubstaff-mcp
Version: 0.1.3
Summary: MCP server for Hubstaff API integration
Project-URL: Homepage, https://github.com/yourusername/hubstaff-mcp
Project-URL: Repository, https://github.com/yourusername/hubstaff-mcp
Project-URL: Issues, https://github.com/yourusername/hubstaff-mcp/issues
Author-email: Your Name <your.email@example.com>
License: MIT
License-File: LICENSE
Keywords: api,hubstaff,mcp,model-context-protocol,time-tracking
Classifier: Development Status :: 3 - Alpha
Classifier: Intended Audience :: Developers
Classifier: License :: OSI Approved :: MIT License
Classifier: Programming Language :: Python :: 3
Classifier: Programming Language :: Python :: 3.10
Classifier: Programming Language :: Python :: 3.11
Classifier: Programming Language :: Python :: 3.12
Requires-Python: >=3.10
Requires-Dist: httpx>=0.25.0
Requires-Dist: mcp>=1.2.0
Requires-Dist: pydantic>=2.0.0
Requires-Dist: python-dotenv>=1.0.0
Provides-Extra: dev
Requires-Dist: black>=23.0.0; extra == 'dev'
Requires-Dist: mypy>=1.0.0; extra == 'dev'
Requires-Dist: pytest-asyncio>=0.21.0; extra == 'dev'
Requires-Dist: pytest>=7.0.0; extra == 'dev'
Requires-Dist: ruff>=0.1.2; extra == 'dev'
